Metadata-Version: 2.1
Name: azjwt
Version: 0.1.1
Summary: Tools for Azure Actve Directory JWT tokens
Home-page: https://github.com/ivangeorgiev/aad-jwt
Author: Ivan Georgiev
License: Creative Commons
Keywords: authentication,azure,jwt
Platform: UNKNOWN
Classifier: Development Status :: 4 - Beta
Classifier: Intended Audience :: Developers
Classifier: License :: OSI Approved :: MIT License
Classifier: Operating System :: OS Independent
Classifier: Programming Language :: Python
Classifier: Programming Language :: Python :: 3
Classifier: Programming Language :: Python :: 3 :: Only
Classifier: Programming Language :: Python :: 3.8
Classifier: Programming Language :: Python :: 3.9
Classifier: Programming Language :: Python :: 3.10
Classifier: Programming Language :: Python :: 3.11
Provides-Extra: test
Provides-Extra: develop
Provides-Extra: docs
